{"expireTime":9007200878854332000,"key":"gatsby-plugin-mdx-entire-payload-068af17571c457949734204241118a3f--undefined","val":{"mdast":{"type":"root","children":[{"type":"heading","depth":1,"children":[{"type":"text","value":"My Past Projects","position":{"start":{"line":2,"column":3,"offset":3},"end":{"line":2,"column":19,"offset":19},"indent":[]}}],"position":{"start":{"line":2,"column":1,"offset":1},"end":{"line":2,"column":19,"offset":19},"indent":[]}},{"type":"heading","depth":2,"children":[{"type":"text","value":"Portfolio Website","position":{"start":{"line":4,"column":4,"offset":24},"end":{"line":4,"column":21,"offset":41},"indent":[]}}],"position":{"start":{"line":4,"column":1,"offset":21},"end":{"line":4,"column":21,"offset":41},"indent":[]}},{"type":"jsx","value":"<LinkImage url=\"#\" file=\"kayaking.png\" title=\"Kayaking\" />","position":{"start":{"line":6,"column":1,"offset":43},"end":{"line":6,"column":59,"offset":101},"indent":[]}},{"type":"paragraph","children":[{"type":"text","value":"This is the description for my portfolio website","position":{"start":{"line":8,"column":1,"offset":103},"end":{"line":8,"column":49,"offset":151},"indent":[]}}],"position":{"start":{"line":8,"column":1,"offset":103},"end":{"line":8,"column":49,"offset":151},"indent":[]}},{"type":"jsx","value":"<ProjectInfo\n  tags={[\"React\", \"Gatsby\", \"MDX\", \"Template\", \"Gatsby Starters\"]}\n  links={[\n    {\n      title: \"Github\",\n      url: \"https://github.com/kaleblub/kaleblub.github.io\",\n    },\n    {\n      title: \"Source\",\n      url: \"#\",\n    },\n  ]}\n/>","position":{"start":{"line":10,"column":1,"offset":153},"end":{"line":22,"column":3,"offset":400},"indent":[1,1,1,1,1,1,1,1,1,1,1,1]}},{"type":"heading","depth":2,"children":[{"type":"text","value":"Python Freerice Bot","position":{"start":{"line":24,"column":4,"offset":405},"end":{"line":24,"column":23,"offset":424},"indent":[]}}],"position":{"start":{"line":24,"column":1,"offset":402},"end":{"line":24,"column":23,"offset":424},"indent":[]}},{"type":"jsx","value":"<LinkImage url=\"#\" file=\"adgp2019.png\" title=\"ADGP 2019\" />","position":{"start":{"line":26,"column":1,"offset":426},"end":{"line":26,"column":60,"offset":485},"indent":[]}},{"type":"paragraph","children":[{"type":"text","value":"This is the description for my python freerice bot program.","position":{"start":{"line":28,"column":1,"offset":487},"end":{"line":28,"column":60,"offset":546},"indent":[]}}],"position":{"start":{"line":28,"column":1,"offset":487},"end":{"line":28,"column":60,"offset":546},"indent":[]}},{"type":"jsx","value":"<ProjectInfo\n  tags={[\"Python\", \"Bot\", \"Web Scraping\", \"Automation\"]}\n  links={[\n    {\n      title: \"Github\",\n      url: \"https://github.com/kaleblub/python-freerice-bot\",\n    },\n    {\n      title: \"\",\n      url: \"#\",\n    },\n  ]}\n/>","position":{"start":{"line":30,"column":1,"offset":548},"end":{"line":42,"column":3,"offset":780},"indent":[1,1,1,1,1,1,1,1,1,1,1,1]}},{"type":"export","value":"export const _frontmatter = {\"title\":\"Works\",\"description\":\"This is my custom description.\",\"image\":\"collins-square.jpg\"}","position":{"start":{"line":45,"column":1,"offset":783},"end":{"line":45,"column":122,"offset":904},"indent":[]}}],"position":{"start":{"line":1,"column":1,"offset":0},"end":{"line":45,"column":122,"offset":904}}},"scopeImports":["import * as React from 'react'"],"scopeIdentifiers":["React"],"body":"var _excluded = [\"components\"];\n\nfunction _extends() { _extends = Object.assign || function (target) { for (var i = 1; i < arguments.length; i++) { var source = arguments[i]; for (var key in source) { if (Object.prototype.hasOwnProperty.call(source, key)) { target[key] = source[key]; } } } return target; }; return _extends.apply(this, arguments); }\n\nfunction _objectWithoutProperties(source, excluded) { if (source == null) return {}; var target = _objectWithoutPropertiesLoose(source, excluded); var key, i; if (Object.getOwnPropertySymbols) { var sourceSymbolKeys = Object.getOwnPropertySymbols(source); for (i = 0; i < sourceSymbolKeys.length; i++) { key = sourceSymbolKeys[i]; if (excluded.indexOf(key) >= 0) continue; if (!Object.prototype.propertyIsEnumerable.call(source, key)) continue; target[key] = source[key]; } } return target; }\n\nfunction _objectWithoutPropertiesLoose(source, excluded) { if (source == null) return {}; var target = {}; var sourceKeys = Object.keys(source); var key, i; for (i = 0; i < sourceKeys.length; i++) { key = sourceKeys[i]; if (excluded.indexOf(key) >= 0) continue; target[key] = source[key]; } return target; }\n\n/* @jsxRuntime classic */\n\n/* @jsx mdx */\nvar _frontmatter = {\n  \"title\": \"Works\",\n  \"description\": \"This is my custom description.\",\n  \"image\": \"collins-square.jpg\"\n};\n\nvar makeShortcode = function makeShortcode(name) {\n  return function MDXDefaultShortcode(props) {\n    console.warn(\"Component \" + name + \" was not imported, exported, or provided by MDXProvider as global scope\");\n    return mdx(\"div\", props);\n  };\n};\n\nvar LinkImage = makeShortcode(\"LinkImage\");\nvar ProjectInfo = makeShortcode(\"ProjectInfo\");\nvar layoutProps = {\n  _frontmatter: _frontmatter\n};\nvar MDXLayout = \"wrapper\";\nreturn function MDXContent(_ref) {\n  var components = _ref.components,\n      props = _objectWithoutProperties(_ref, _excluded);\n\n  return mdx(MDXLayout, _extends({}, layoutProps, props, {\n    components: components,\n    mdxType: \"MDXLayout\"\n  }), mdx(\"h1\", null, \"My Past Projects\"), mdx(\"h2\", null, \"Portfolio Website\"), mdx(LinkImage, {\n    url: \"#\",\n    file: \"kayaking.png\",\n    title: \"Kayaking\",\n    mdxType: \"LinkImage\"\n  }), mdx(\"p\", null, \"This is the description for my portfolio website\"), mdx(ProjectInfo, {\n    tags: [\"React\", \"Gatsby\", \"MDX\", \"Template\", \"Gatsby Starters\"],\n    links: [{\n      title: \"Github\",\n      url: \"https://github.com/kaleblub/kaleblub.github.io\"\n    }, {\n      title: \"Source\",\n      url: \"#\"\n    }],\n    mdxType: \"ProjectInfo\"\n  }), mdx(\"h2\", null, \"Python Freerice Bot\"), mdx(LinkImage, {\n    url: \"#\",\n    file: \"adgp2019.png\",\n    title: \"ADGP 2019\",\n    mdxType: \"LinkImage\"\n  }), mdx(\"p\", null, \"This is the description for my python freerice bot program.\"), mdx(ProjectInfo, {\n    tags: [\"Python\", \"Bot\", \"Web Scraping\", \"Automation\"],\n    links: [{\n      title: \"Github\",\n      url: \"https://github.com/kaleblub/python-freerice-bot\"\n    }, {\n      title: \"\",\n      url: \"#\"\n    }],\n    mdxType: \"ProjectInfo\"\n  }));\n}\n;\nMDXContent.isMDXComponent = true;","rawMDXOutput":"/* @jsx mdx */\nimport { mdx } from '@mdx-js/react';\n/* @jsxRuntime classic */\n/* @jsx mdx */\n\nexport const _frontmatter = {\n  \"title\": \"Works\",\n  \"description\": \"This is my custom description.\",\n  \"image\": \"collins-square.jpg\"\n};\nconst makeShortcode = name => function MDXDefaultShortcode(props) {\n      console.warn(\"Component \" + name + \" was not imported, exported, or provided by MDXProvider as global scope\")\n      return <div {...props}/>\n    };\nconst LinkImage = makeShortcode(\"LinkImage\");\nconst ProjectInfo = makeShortcode(\"ProjectInfo\");\nconst layoutProps = {\n  _frontmatter\n};\nconst MDXLayout = \"wrapper\"\nexport default function MDXContent({\n  components,\n  ...props\n}) {\n  return <MDXLayout {...layoutProps} {...props} components={components} mdxType=\"MDXLayout\">\n    <h1>{`My Past Projects`}</h1>\n    <h2>{`Portfolio Website`}</h2>\n    <LinkImage url=\"#\" file=\"kayaking.png\" title=\"Kayaking\" mdxType=\"LinkImage\" />\n    <p>{`This is the description for my portfolio website`}</p>\n    <ProjectInfo tags={[\"React\", \"Gatsby\", \"MDX\", \"Template\", \"Gatsby Starters\"]} links={[{\n      title: \"Github\",\n      url: \"https://github.com/kaleblub/kaleblub.github.io\"\n    }, {\n      title: \"Source\",\n      url: \"#\"\n    }]} mdxType=\"ProjectInfo\" />\n    <h2>{`Python Freerice Bot`}</h2>\n    <LinkImage url=\"#\" file=\"adgp2019.png\" title=\"ADGP 2019\" mdxType=\"LinkImage\" />\n    <p>{`This is the description for my python freerice bot program.`}</p>\n    <ProjectInfo tags={[\"Python\", \"Bot\", \"Web Scraping\", \"Automation\"]} links={[{\n      title: \"Github\",\n      url: \"https://github.com/kaleblub/python-freerice-bot\"\n    }, {\n      title: \"\",\n      url: \"#\"\n    }]} mdxType=\"ProjectInfo\" />\n\n    </MDXLayout>;\n}\n\n;\nMDXContent.isMDXComponent = true;"}}